frads/__init__.py
frads/ep2rad.py
frads/eplus.py
frads/eplus_model.py
frads/geom.py
frads/matrix.py
frads/methods.py
frads/room.py
frads/sky.py
frads/utils.py
frads/window.py
frads-2.1.14.dist-info/METADATA
frads-2.1.14.dist-info/WHEEL
frads-2.1.14.dist-info/top_level.txt
frads-2.1.14.dist-info/RECORD
