Metadata-Version: 2.4
Name: frads
Version: 2.1.14
Summary: Framework for lighting and energy simulations
Author-email: LBNL <taoningwang@lbl.gov>
License: *** License Agreement ***
Requires-Python: >=3.10
Requires-Dist: epmodel==0.10.0
Requires-Dist: numpy>=1.24.4
Requires-Dist: pyradiance==1.1.5
Requires-Dist: pywincalc>=3.1.0
Requires-Dist: pyenergyplus_lbnl==25.1.2
Requires-Dist: scipy>=1.10.1
